{
	"pages": [ //pages数组中第一项表示应用启动页，参考：https://uniapp.dcloud.io/collocation/pages
		{
			"path": "pages/home/home",
			"style": {
				"navigationBarTitleText": "我的"
			}
		}, {
			"path": "pages/cart/cart",
			"style": {
				"navigationBarTitleText": "购物车"
			}
		}, {
			"path": "pages/vip/vip",
			"style": {
				"navigationBarTitleText": "会员"
			}
		}, {
			"path": "pages/news/news",
			"style": {
				"navigationBarTitleText": "资讯"
			}
		}, {
			"path": "pages/home/home",
			"style": {
				"navigationBarTitleText": "首页"
			}
		}
	],
	"globalStyle": {
		"navigationBarTextStyle": "white",
		"navigationBarTitleText": "商城应用",
		"navigationBarBackgroundColor": "#b50e03",
		"backgroundColor": "#F8F8F8"
	},
	"tabBar": {
		"color": "#7A7E83",
		"selectedColor": "#b50e03",
		"borderStyle": "black",
		"backgroundColor": "#ffffff",
		"list": [{
				"text": "首页",
				"pagePath": "pages/home/home",
				"iconPath": "static/tabs/home1.png",
				"selectedIconPath": "static/tabs/home2.png"
			},
			{
				"text": "购物车",
				"pagePath": "pages/cart/cart",
				"iconPath": "static/tabs/cart1.png",
				"selectedIconPath": "static/tabs/cart2.png"
			},
			{
				"text": "会员",
				"pagePath": "pages/vip/vip",
				"iconPath": "static/tabs/vip1.png",
				"selectedIconPath": "static/tabs/vip2.png"
			},
			{
				"text": "资讯",
				"pagePath": "pages/news/news",
				"iconPath": "static/tabs/news1.png",
				"selectedIconPath": "static/tabs/news2.png"
			}
		]
	}
}
